spirems/__init__.py
spirems/client.py
spirems/core.py
spirems/error_code.py
spirems/log.py
spirems/log2sms.py
spirems/logsaver.py
spirems/mod_helper.py
spirems/msg_helper.py
spirems/parameter.py
spirems/publisher.py
spirems/service.py
spirems/sms.py
spirems/smsbag.py
spirems/smsparam.py
spirems/smsservice.py
spirems/subscriber.py
spirems/demo/__init__.py
spirems/demo/a2rl_path_sender.py
spirems/demo/drone_pose_rec.py
spirems/demo/publisher_demo.py
spirems/demo/pybind_demo.py
spirems/demo/ros1_image_receiver_test.py
spirems/demo/ros1_image_sender_test.py
spirems/demo/ros2_a2rl_3lidar_concat.py
spirems/demo/ros2_a2rl_lidar2sms.py
spirems/demo/ros2_image_receiver_test.py
spirems/demo/ros2_image_sender_test.py
spirems/demo/service_demo.py
spirems/demo/subscriber_demo.py
spirems/demo/tensor_mem_demo.py
spirems/demo/tensor_mem_pub_demo.py
spirems/demo/tensor_mem_sub_demo.py
spirems/exts/__init__.py
spirems/foxglove/__init__.py
spirems/foxglove/foxglove_server.py
spirems/foxglove/middleware.py
spirems/foxglove/schema/ArrowPrimitive.json
spirems/foxglove/schema/CameraCalibration.json
spirems/foxglove/schema/CircleAnnotation.json
spirems/foxglove/schema/Color.json
spirems/foxglove/schema/CompressedImage.json
spirems/foxglove/schema/CompressedVideo.json
spirems/foxglove/schema/CubePrimitive.json
spirems/foxglove/schema/CylinderPrimitive.json
spirems/foxglove/schema/FrameTransform.json
spirems/foxglove/schema/FrameTransforms.json
spirems/foxglove/schema/GeoJSON.json
spirems/foxglove/schema/Grid.json
spirems/foxglove/schema/ImageAnnotations.json
spirems/foxglove/schema/KeyValuePair.json
spirems/foxglove/schema/LaserScan.json
spirems/foxglove/schema/LinePrimitive.json
spirems/foxglove/schema/LocationFix.json
spirems/foxglove/schema/Log.json
spirems/foxglove/schema/ModelPrimitive.json
spirems/foxglove/schema/PackedElementField.json
spirems/foxglove/schema/Point2.json
spirems/foxglove/schema/Point3.json
spirems/foxglove/schema/PointCloud.json
spirems-0.7.5.dist-info/licenses/LICENSE
spirems-0.7.5.dist-info/METADATA
spirems-0.7.5.dist-info/WHEEL
spirems-0.7.5.dist-info/entry_points.txt
spirems-0.7.5.dist-info/top_level.txt
spirems-0.7.5.dist-info/RECORD
