Metadata-Version: 2.4
Name: spirems
Version: 0.7.5
Summary: Spire message system, a lightweight message publishing and subscription software package similar to ROS.
Author: jario
Author-email: jario <renjin@bit.edu.cn>
Maintainer-email: jario <renjin@bit.edu.cn>
License: Apache-2.0
Project-URL: Homepage, https://www.wolai.com/duBWkKUCYQJCVSGPwueCrx
Project-URL: Source, https://gitee.com/jario-jin/spirems
Project-URL: Documentation, https://www.wolai.com/duBWkKUCYQJCVSGPwueCrx
Project-URL: Bug Reports, https://gitee.com/jario-jin/spirems/issues
Project-URL: Changelog, https://gitee.com/jario-jin/spirems/releases
Keywords: message-system,lightweight,computer-vision,SpireMS
Classifier: Development Status :: 4 - Beta
Classifier: Intended Audience :: Developers
Classifier: Intended Audience :: Education
Classifier: Intended Audience :: Science/Research
Classifier: License :: OSI Approved :: Apache Software License
Classifier: Programming Language :: Python :: 3
Classifier: Programming Language :: Python :: 3.8
Classifier: Programming Language :: Python :: 3.9
Classifier: Programming Language :: Python :: 3.10
Classifier: Programming Language :: Python :: 3.11
Classifier: Programming Language :: Python :: 3.12
Classifier: Topic :: Software Development
Classifier: Topic :: Scientific/Engineering
Classifier: Topic :: Scientific/Engineering :: Artificial Intelligence
Classifier: Operating System :: POSIX :: Linux
Classifier: Operating System :: MacOS
Classifier: Operating System :: Microsoft :: Windows
Requires-Python: >=3.8
License-File: LICENSE
Requires-Dist: numpy
Requires-Dist: opencv-python
Requires-Dist: psutil
Requires-Dist: colorama
Requires-Dist: foxglove_websocket
Requires-Dist: requests
Requires-Dist: mcap
Provides-Extra: extra
Requires-Dist: pynvjpeg; extra == "extra"
Dynamic: author
Dynamic: license-file
Dynamic: requires-python
